easy_split
