Metadata-Version: 1.0
Name: django-easy-split
Version: 0.1.3
Summary: Super easy split testing for your Django projects.
Home-page: https://github.com/Miserlou/django-easy-split
Author: Rich Jones
Author-email: rich@openwatch.net
License: MIT License
Platform: UNKNOWN
Classifier: Environment :: Web Environment
Classifier: Framework :: Django
Classifier: Intended Audience :: Developers
Classifier: License :: OSI Approved :: Apache Software License
Classifier: Operating System :: OS Independent
Classifier: Programming Language :: Python
Classifier: Programming Language :: Python :: 2.6
Classifier: Programming Language :: Python :: 2.7
Classifier: Topic :: Internet :: WWW/HTTP
Classifier: Topic :: Internet :: WWW/HTTP :: Dynamic Content
